pycamel/__init__.py
pycamel/src/__init__.py
pycamel/src/enums/__init__.py
pycamel/src/enums/assert_conditions.py
pycamel/src/errors/SystemErrors.py
pycamel/src/errors/ValidationErrors.py
pycamel/src/errors/__init__.py
pycamel/src/modules/__init__.py
pycamel/src/modules/core/__init__.py
pycamel/src/modules/core/config.py
pycamel/src/modules/core/filter.py
pycamel/src/modules/core/validator.py
pycamel/src/modules/response/__init__.py
pycamel/src/modules/response/response.py
pycamel/src/modules/routing/__init__.py
pycamel/src/modules/routing/router.py
pycamel/src/modules/routing/router_maker.py
pycamel/src/utils/__init__.py
pycamel/src/utils/camel_enum.py
pycamel/src/utils/search_key_processor.py
pycamel/src/utils/searcher.py
tests/__init__.py
tests/conftest.py
tests/test_config.py
tests/test_enum.py
tests/test_filtering.py
tests/test_project_key_searcher.py
tests/test_response.py
tests/test_router.py
tests/test_router_maker.py
tests/test_searcher.py
tests/test_validator.py
pycamel-1.0.4.dist-info/LICENSE
pycamel-1.0.4.dist-info/METADATA
pycamel-1.0.4.dist-info/WHEEL
pycamel-1.0.4.dist-info/top_level.txt
pycamel-1.0.4.dist-info/RECORD
