Metadata-Version: 2.1
Name: pycamel
Version: 1.0.4
Summary: Backend automation framework. Automation is easy.
Home-page: https://github.com/canyoupleasecreateanaccount/pycamel
Author: Yurii Abramenko
Author-email: <yura.abramenko1@gmail.com>
License: Apache License, Version 2.0, see LICENSE file
Project-URL: Source, https://github.com/canyoupleasecreateanaccount/pycamel/
Project-URL: Tracker, https://github.com/canyoupleasecreateanaccount/pycamel/issues
Project-URL: Changelog, https://github.com/canyoupleasecreateanaccount/pycamel/releases
Keywords: python,automation,testing,tests,backend automation,pytests,pydantic
Classifier: License :: OSI Approved :: Apache Software License
Classifier: Development Status :: 5 - Production/Stable
Classifier: Intended Audience :: Developers
Classifier: Programming Language :: Python :: 3.0
Classifier: Programming Language :: Python :: 3.1
Classifier: Programming Language :: Python :: 3.2
Classifier: Programming Language :: Python :: 3.3
Classifier: Programming Language :: Python :: 3.4
Classifier: Programming Language :: Python :: 3.5
Classifier: Programming Language :: Python :: 3.6
Classifier: Programming Language :: Python :: 3.7
Classifier: Programming Language :: Python :: 3.8
Classifier: Programming Language :: Python :: 3.9
Classifier: Programming Language :: Python :: 3.10
Classifier: Programming Language :: Python :: 3.11
Classifier: Programming Language :: Python :: 3.12
Classifier: Operating System :: OS Independent
Classifier: Framework :: Pytest
License-File: LICENSE
Requires-Dist: pydantic
Requires-Dist: requests
